{
  "annotations": {
    "changelogDate": "20251216065250"
  },
  "applications": ["monsterdamChicks"],
  "dto": "mapstruct",
  "fields": [
    {
      "fieldName": "question",
      "fieldType": "TextBlob",
      "fieldValidateRules": ["required"]
    },
    {
      "fieldName": "isMultiChoice",
      "fieldType": "Boolean",
      "fieldValidateRules": ["required"]
    },
    {
      "fieldName": "endDate",
      "fieldType": "LocalDate",
      "fieldValidateRules": ["required"]
    },
    {
      "fieldName": "duration",
      "fieldType": "Duration",
      "fieldValidateRules": ["required"]
    },
    {
      "fieldName": "createdDate",
      "fieldType": "Instant",
      "fieldValidateRules": ["required"]
    },
    {
      "fieldName": "lastModifiedDate",
      "fieldType": "Instant"
    },
    {
      "fieldName": "createdBy",
      "fieldType": "String"
    },
    {
      "fieldName": "lastModifiedBy",
      "fieldType": "String"
    },
    {
      "fieldName": "deletedDate",
      "fieldType": "Instant"
    }
  ],
  "name": "PostPoll",
  "pagination": "pagination",
  "relationships": [
    {
      "otherEntityName": "postFeed",
      "otherEntityRelationshipName": "polls",
      "relationshipName": "post",
      "relationshipSide": "left",
      "relationshipType": "many-to-one",
      "relationshipValidateRules": "required"
    }
  ],
  "searchEngine": "no",
  "service": "serviceImpl"
}
